toolboks/__init__.py
toolboks/_version.py
toolboks/config.py
toolboks/listlib.py
toolboks/modifiers.py
toolboks/system.py
toolboks/xdg.py
toolboks-0.0.2.dist-info/LICENSE
toolboks-0.0.2.dist-info/METADATA
toolboks-0.0.2.dist-info/WHEEL
toolboks-0.0.2.dist-info/top_level.txt
toolboks-0.0.2.dist-info/RECORD
