Metadata-Version: 2.1
Name: toolboks
Version: 0.0.2
Summary: toolboks utility library
Author: Mikael Tranbom
Author-email: mikael@tranbom.io
License: GPLv3
Project-URL: Homepage, https://gitlab.com/toolboks/toolboks
Project-URL: Repository, https://gitlab.com/toolboks/toolboks
Keywords: utility,developer tools,library,CLI tools
Classifier: Development Status :: 4 - Beta
Classifier: Intended Audience :: Developers
Classifier: License :: OSI Approved :: GNU General Public License v3 (GPLv3)
Classifier: Natural Language :: English
Classifier: Operating System :: OS Independent
Classifier: Programming Language :: Python
Classifier: Programming Language :: Python :: 3
Classifier: Programming Language :: Python :: 3.9
Classifier: Programming Language :: Python :: 3.10
Classifier: Programming Language :: Python :: 3.11
Classifier: Topic :: Software Development
Classifier: Topic :: Utilities
Requires-Python: >=3.9
License-File: LICENSE
